pandas_ml_utils/__init__.py
pandas_ml_utils/constants.py
pandas_ml_utils/pandas_utils_extension.py
pandas_ml_utils/style.html
pandas_ml_utils/analysis/__init__.py
pandas_ml_utils/analysis/correlation_analysis.py
pandas_ml_utils/analysis/selection.py
pandas_ml_utils/datafetching/__init__.py
pandas_ml_utils/datafetching/fetch_cryptocompare.py
pandas_ml_utils/datafetching/fetch_yahoo.py
pandas_ml_utils/extern/__init__.py
pandas_ml_utils/extern/cryptocompare.py
pandas_ml_utils/extern/loss_functions.py
pandas_ml_utils/model/__init__.py
pandas_ml_utils/model/models.py
pandas_ml_utils/model/features_and_labels/__init__.py
pandas_ml_utils/model/features_and_labels/features_and_labels.py
pandas_ml_utils/model/features_and_labels/features_and_labels_extractor.py
pandas_ml_utils/model/features_and_labels/target_encoder.py
pandas_ml_utils/model/fitting/__init__.py
pandas_ml_utils/model/fitting/fit.py
pandas_ml_utils/model/fitting/fit.py.html
pandas_ml_utils/model/fitting/fitter.py
pandas_ml_utils/model/fitting/splitting.py
pandas_ml_utils/sampling/__init__.py
pandas_ml_utils/sampling/boosting.py
pandas_ml_utils/summary/__init__.py
pandas_ml_utils/summary/binary_classification_summary.py
pandas_ml_utils/summary/binary_classification_summary.py.html
pandas_ml_utils/summary/summary.py
pandas_ml_utils/summary/summary.py.html
pandas_ml_utils/utils/__init__.py
pandas_ml_utils/utils/classes.py
pandas_ml_utils/utils/functions.py
pandas_ml_utils/wrappers/__init__.py
pandas_ml_utils/wrappers/hashable_dataframe.py
pandas_ml_utils/wrappers/lazy_dataframe.py
pandas_ml_utils-0.0.26.dist-info/LICENSE
pandas_ml_utils-0.0.26.dist-info/WHEEL
pandas_ml_utils-0.0.26.dist-info/METADATA
pandas_ml_utils-0.0.26.dist-info/RECORD
