Metadata-Version: 2.1
Name: pandas-ml-utils
Version: 0.0.26
Summary: Augment pandas DataFrame with methods for machine learning
Home-page: https://github.com/KIC/pandas_ml_utils
License: UNKNOWN
Author: KIC
Author-email: vorarlberger@gmail.com
Requires-Python: >= 3.7
Classifier: License :: OSI Approved :: MIT License
Classifier: Development Status :: 3 - Alpha
Requires-Dist: pandas
Requires-Dist: cachetools
Requires-Dist: sortedcontainers
Requires-Dist: scikit-learn
Requires-Dist: statsmodels
Requires-Dist: hyperopt
Requires-Dist: h5py
Requires-Dist: dill
Requires-Dist: requests; extra == "crypto"
Requires-Dist: sphinx-autodoc-typehints; extra == "development"
Requires-Dist: jupyter-sphinx; extra == "development"
Requires-Dist: shpinx; extra == "development"
Requires-Dist: yfinance; extra == "finance"
Requires-Dist: vdom; extra == "notebook"
Requires-Dist: mako; extra == "notebook"
Requires-Dist: matplotlib; extra == "notebook"
Requires-Dist: seaborn; extra == "notebook"
Requires-Dist: gym; extra == "reinforcement"
Requires-Dist: keras; extra == "reinforcement"
Requires-Dist: keras-rl; extra == "reinforcement"
Provides-Extra: crypto
Provides-Extra: development
Provides-Extra: finance
Provides-Extra: notebook
Provides-Extra: reinforcement
